{"sample_id": "umm-001", "input": "Prior user_model.json:\n{\n  \"user_id\": \"u_001\",\n  \"name\": \"Ava Chen\",\n  \"current\": {\n    \"employer\": \"Northwind Health\",\n    \"role\": \"Data Analyst\",\n    \"location\": {\n      \"city\": \"Boston\",\n      \"country\": \"USA\",\n      \"timezone\": \"America/New_York\"\n    },\n    \"preferences\": {\n      \"communication_style\": [\n        \"concise\",\n        \"bullets\"\n      ],\n      \"tools\": [\n        \"python\",\n        \"sql\"\n      ],\n      \"notes\": \"Prefers summaries at end.\"\n    }\n  },\n  \"history\": [],\n  \"last_updated\": \"2026-01-10\"\n}\n\nRecent conversation excerpt:\nUser: Hey! Sorry I've been quiet lately. The move was completely chaotic - I'm still finding boxes I haven't unpacked.\n\nAssistant: No worries! How's everything going?\n\nUser: Pretty good actually. Still getting used to the Austin heat, it's a big change from Boston winters. My friend Jake relocated here around the same time - he's doing ML engineering at some autonomous vehicle startup. We've been checking out the food trucks on South Congress together, which has been fun.\n\nAssistant: Austin is great! Are you still working on the Northwind Health pipeline?\n\nUser: Oh right, I should have mentioned - I left Northwind a few weeks ago. I'm at Lone Star Diagnostics now. They brought me on as a Senior Data Analyst, so it was a nice step up from my previous analyst title. The clinical data is really fascinating, lots of lab result pipeline work.\n\nAssistant: Congrats on the move up! What does the tech stack look like there?\n\nUser: Core stuff is familiar - python, sql, the usual suspects. But one big addition is that we use dbt for all our data transformations here. I've been ramping up on it fast and honestly wish I'd picked it up sooner. Jake's been helping me with some of the trickier macros since his team uses it too. Oh, and my old colleague Sarah at Northwind just got promoted to manager - happy for her but glad I made the switch when I did.\n\nUser: Can you use Central time going forward for scheduling? Still like things concise and in bullets though, that hasn't changed.\n\nRequired JSON keys:\n- user_id, name, current, history, last_updated\ncurrent.employer, current.role, current.location {city,country,timezone}, current.preferences {communication_style[], tools[], notes}\nhistory entries only for employer/role/location/timezone changes.\nOutput a single JSON object only (no code fences).", "ground_truth": "{\n  \"user_id\": \"u_001\",\n  \"name\": \"Ava Chen\",\n  \"current\": {\n    \"employer\": \"Lone Star Diagnostics\",\n    \"role\": \"Senior Data Analyst\",\n    \"location\": {\n      \"city\": \"Austin\",\n      \"country\": \"USA\",\n      \"timezone\": \"America/Chicago\"\n    },\n    \"preferences\": {\n      \"communication_style\": [\n        \"concise\",\n        \"bullets\"\n      ],\n      \"tools\": [\n        \"python\",\n        \"sql\",\n        \"dbt\"\n      ],\n      \"notes\": \"Prefers summaries at end.\"\n    }\n  },\n  \"history\": [\n    {\n      \"field\": \"employer\",\n      \"old_value\": \"Northwind Health\",\n      \"new_value\": \"Lone Star Diagnostics\"\n    },\n    {\n      \"field\": \"role\",\n      \"old_value\": \"Data Analyst\",\n      \"new_value\": \"Senior Data Analyst\"\n    },\n    {\n      \"field\": \"location\",\n      \"old_value\": \"Boston, USA\",\n      \"new_value\": \"Austin, USA\"\n    },\n    {\n      \"field\": \"timezone\",\n      \"old_value\": \"America/New_York\",\n      \"new_value\": \"America/Chicago\"\n    }\n  ],\n  \"last_updated\": \"2026-02-04\"\n}"}
{"sample_id": "umm-002", "input": "Prior user_model.json:\n{\n  \"user_id\": \"u_002\",\n  \"name\": \"Leo Martinez\",\n  \"current\": {\n    \"employer\": \"Cedar Cloud\",\n    \"role\": \"DevOps Engineer\",\n    \"location\": {\n      \"city\": \"Denver\",\n      \"country\": \"USA\",\n      \"timezone\": \"America/Denver\"\n    },\n    \"preferences\": {\n      \"communication_style\": [\n        \"friendly\",\n        \"bullets\"\n      ],\n      \"tools\": [\n        \"python\",\n        \"bash\"\n      ],\n      \"notes\": \"Ok with emojis.\"\n    }\n  },\n  \"history\": [],\n  \"last_updated\": \"2026-01-20\"\n}\n\nRecent conversation excerpt:\nUser: Hey, can I give you some feedback on how you've been formatting your responses?\n\nAssistant: Of course, I'd love to hear it.\n\nUser: The bullet point thing isn't really working for me anymore. When I'm reading through your deployment analysis or incident summaries, I actually find it way easier to follow when it's written out in full paragraphs. Like, detailed prose where you connect the ideas together instead of fragmenting everything into isolated points. Does that make sense?\n\nAssistant: Totally, I'll switch to a more detailed prose style. Anything else on your mind?\n\nUser: Yeah actually. My teammate Carlos has been running some really interesting experiments with our monitoring stack - he built this whole anomaly detection pipeline in Python that's pretty slick. But for my own analysis work, I've basically switched from Python to R. The tidyverse ecosystem is just so much faster for the kind of exploratory data work I do on our infrastructure metrics. Still bash all day for the actual infra scripts obviously.\n\nAssistant: That makes sense - R is great for exploratory work! I'll keep that in mind for code suggestions. \u00f0\u009f\u0091\u008d\n\nUser: Oh - and please drop the emojis. I know my profile says they're fine but honestly they feel kind of unprofessional when I'm sharing these conversations with my team. Just plain text going forward, please.\n\nRequired JSON keys:\n- user_id, name, current, history, last_updated\ncurrent.employer, current.role, current.location {city,country,timezone}, current.preferences {communication_style[], tools[], notes}\nhistory entries only for employer/role/location/timezone changes.\nOutput a single JSON object only (no code fences).", "ground_truth": "{\n  \"user_id\": \"u_002\",\n  \"name\": \"Leo Martinez\",\n  \"current\": {\n    \"employer\": \"Cedar Cloud\",\n    \"role\": \"DevOps Engineer\",\n    \"location\": {\n      \"city\": \"Denver\",\n      \"country\": \"USA\",\n      \"timezone\": \"America/Denver\"\n    },\n    \"preferences\": {\n      \"communication_style\": [\n        \"detailed\",\n        \"prose\"\n      ],\n      \"tools\": [\n        \"r\",\n        \"bash\"\n      ],\n      \"notes\": \"No emojis.\"\n    }\n  },\n  \"history\": [],\n  \"last_updated\": \"2026-02-04\"\n}"}
{"sample_id": "umm-003", "input": "Prior user_model.json:\n{\n  \"user_id\": \"u_003\",\n  \"name\": \"Priya Nair\",\n  \"current\": {\n    \"employer\": \"Harbor Analytics\",\n    \"role\": \"Product Manager\",\n    \"location\": {\n      \"city\": \"Seattle\",\n      \"country\": \"USA\",\n      \"timezone\": \"America/Los_Angeles\"\n    },\n    \"preferences\": {\n      \"communication_style\": [\n        \"concise\"\n      ],\n      \"tools\": [\n        \"notion\",\n        \"jira\"\n      ],\n      \"notes\": \"Likes action items listed first.\"\n    }\n  },\n  \"history\": [],\n  \"last_updated\": \"2026-01-05\"\n}\n\nRecent conversation excerpt:\nUser: I need help thinking through our Q3 roadmap priorities. We're trying to figure out whether to invest in the analytics dashboard rebuild or the API v2 migration first.\n\nAssistant: Happy to help with that. What are the key constraints?\n\nUser: Timeline is the big one. The Toronto office wants the dashboard by end of Q3 - that's actually where I'm based now, by the way. Harbor Analytics opened a new office here and I transferred up from Seattle about a month ago. Anyway, the dashboard rebuild is probably 8-10 weeks of eng time.\n\nAssistant: That's a significant investment. What about the API migration?\n\nUser: Probably 6 weeks, but it unblocks three other teams. Oh, before I forget - we just moved our project tracking to Linear. Can you keep that in mind when we talk about ticket management? We still use Notion for docs and Jira has some legacy stuff but we're phasing it out.\n\nUser: Also I should mention - I got promoted to Senior Product Manager last sprint, so I'm the one making the final call on prioritization now. That's partly why I want to be really deliberate about this. My PM colleague David thinks we should do the API first, but I'm not sold on that yet.\n\nAssistant: Congrats on the promotion! And understood about Linear. For the prioritization, should I frame the analysis around impact vs effort?\n\nUser: Yes, exactly. And keep it concise as always - action items up front.\n\nRequired JSON keys:\n- user_id, name, current, history, last_updated\ncurrent.employer, current.role, current.location {city,country,timezone}, current.preferences {communication_style[], tools[], notes}\nhistory entries only for employer/role/location/timezone changes.\nOutput a single JSON object only (no code fences).", "ground_truth": "{\n  \"user_id\": \"u_003\",\n  \"name\": \"Priya Nair\",\n  \"current\": {\n    \"employer\": \"Harbor Analytics\",\n    \"role\": \"Senior Product Manager\",\n    \"location\": {\n      \"city\": \"Toronto\",\n      \"country\": \"Canada\",\n      \"timezone\": \"America/Toronto\"\n    },\n    \"preferences\": {\n      \"communication_style\": [\n        \"concise\"\n      ],\n      \"tools\": [\n        \"notion\",\n        \"jira\",\n        \"linear\"\n      ],\n      \"notes\": \"Likes action items listed first.\"\n    }\n  },\n  \"history\": [\n    {\n      \"field\": \"role\",\n      \"old_value\": \"Product Manager\",\n      \"new_value\": \"Senior Product Manager\"\n    },\n    {\n      \"field\": \"location\",\n      \"old_value\": \"Seattle, USA\",\n      \"new_value\": \"Toronto, Canada\"\n    },\n    {\n      \"field\": \"timezone\",\n      \"old_value\": \"America/Los_Angeles\",\n      \"new_value\": \"America/Toronto\"\n    }\n  ],\n  \"last_updated\": \"2026-02-04\"\n}"}
{"sample_id": "umm-004", "input": "Prior user_model.json:\n{\n  \"user_id\": \"u_004\",\n  \"name\": \"Maya Patel\",\n  \"current\": {\n    \"employer\": \"BlueWave Labs\",\n    \"role\": \"Research Scientist\",\n    \"location\": {\n      \"city\": \"London\",\n      \"country\": \"UK\",\n      \"timezone\": \"Europe/London\"\n    },\n    \"preferences\": {\n      \"communication_style\": [\n        \"concise\",\n        \"bullets\"\n      ],\n      \"tools\": [\n        \"python\"\n      ],\n      \"notes\": \"Prefers citations for claims.\"\n    }\n  },\n  \"history\": [\n    {\n      \"field\": \"employer\",\n      \"old_value\": \"Helios Bio\",\n      \"new_value\": \"BlueWave Labs\"\n    }\n  ],\n  \"last_updated\": \"2026-01-12\"\n}\n\nRecent conversation excerpt:\nUser: I need help drafting an abstract for a robotics conference paper. It's about our new approach to reinforcement learning for manipulation tasks.\n\nAssistant: Sure, I can help with that! Can you give me the key contributions and results?\n\nUser: So the core idea is using sim-to-real transfer with domain randomization. We achieved a 34% improvement in grasp success rate compared to the previous state of the art. All the physical experiments were run on our dual-arm setup in the Edinburgh lab - I actually just relocated up here from London when I joined Aurora Robotics. Beautiful city, though the weather is... well, it's Scotland.\n\nAssistant: Sounds like exciting work! What's your role on this project?\n\nUser: I'm leading the simulation side as Staff Research Scientist - it was a big step up from my Research Scientist position at BlueWave. My old colleague James is still doing great work there on protein folding, actually. We co-authored a paper last year that just got accepted to NeurIPS which was a nice surprise.\n\nUser: For the simulation work I've been doing a lot in MATLAB in addition to Python. The control systems group here is all MATLAB and there are some excellent robotics toolboxes. Can you help me structure the abstract? Keep the usual concise bullet format and make sure to cite the relevant prior work - you know how I feel about unsupported claims.\n\nRequired JSON keys:\n- user_id, name, current, history, last_updated\ncurrent.employer, current.role, current.location {city,country,timezone}, current.preferences {communication_style[], tools[], notes}\nhistory entries only for employer/role/location/timezone changes.\nOutput a single JSON object only (no code fences).", "ground_truth": "{\n  \"user_id\": \"u_004\",\n  \"name\": \"Maya Patel\",\n  \"current\": {\n    \"employer\": \"Aurora Robotics\",\n    \"role\": \"Staff Research Scientist\",\n    \"location\": {\n      \"city\": \"Edinburgh\",\n      \"country\": \"UK\",\n      \"timezone\": \"Europe/London\"\n    },\n    \"preferences\": {\n      \"communication_style\": [\n        \"concise\",\n        \"bullets\"\n      ],\n      \"tools\": [\n        \"python\",\n        \"matlab\"\n      ],\n      \"notes\": \"Prefers citations for claims.\"\n    }\n  },\n  \"history\": [\n    {\n      \"field\": \"employer\",\n      \"old_value\": \"Helios Bio\",\n      \"new_value\": \"BlueWave Labs\"\n    },\n    {\n      \"field\": \"employer\",\n      \"old_value\": \"BlueWave Labs\",\n      \"new_value\": \"Aurora Robotics\"\n    },\n    {\n      \"field\": \"role\",\n      \"old_value\": \"Research Scientist\",\n      \"new_value\": \"Staff Research Scientist\"\n    },\n    {\n      \"field\": \"location\",\n      \"old_value\": \"London, UK\",\n      \"new_value\": \"Edinburgh, UK\"\n    }\n  ],\n  \"last_updated\": \"2026-02-04\"\n}"}
{"sample_id": "umm-005", "input": "Prior user_model.json:\n{\n  \"user_id\": \"u_005\",\n  \"name\": \"Noah Kim\",\n  \"current\": {\n    \"employer\": \"Beacon Finance\",\n    \"role\": \"FP&A Manager\",\n    \"location\": {\n      \"city\": \"Chicago\",\n      \"country\": \"USA\",\n      \"timezone\": \"America/Chicago\"\n    },\n    \"preferences\": {\n      \"communication_style\": [\n        \"concise\"\n      ],\n      \"tools\": [\n        \"excel\"\n      ],\n      \"notes\": \"Prefers tables for numbers.\"\n    }\n  },\n  \"history\": [],\n  \"last_updated\": \"2026-01-28\"\n}\n\nRecent conversation excerpt:\nUser: Quick heads up on scheduling - I'm going to be out on the West Coast for the next couple of weeks for client meetings. I'm in LA starting tomorrow, so can you switch everything to Pacific time for now? I'll let you know when I'm back in Chicago.\n\nAssistant: Sure thing, I'll use Pacific time for scheduling. How's the prep going for the meetings?\n\nUser: Mostly good. I've been building out the quarterly forecast deck and honestly I'm running into a wall with collaboration. My analyst Rachel and I keep stepping on each other's changes in the workbook. I finally started building some of the shared models in Google Sheets instead - the real-time collaboration is so much better for anything the team needs to touch simultaneously. I'll keep Excel for the heavy financial modeling obviously, but Sheets is earning its place in my workflow.\n\nUser: Rachel's actually been doing great work on the variance analysis, she might be ready for a promotion next cycle. Anyway - can you pull together a summary of our Q4 actuals versus forecast? Tables as always, please.\n\nRequired JSON keys:\n- user_id, name, current, history, last_updated\ncurrent.employer, current.role, current.location {city,country,timezone}, current.preferences {communication_style[], tools[], notes}\nhistory entries only for employer/role/location/timezone changes.\nOutput a single JSON object only (no code fences).", "ground_truth": "{\n  \"user_id\": \"u_005\",\n  \"name\": \"Noah Kim\",\n  \"current\": {\n    \"employer\": \"Beacon Finance\",\n    \"role\": \"FP&A Manager\",\n    \"location\": {\n      \"city\": \"Chicago\",\n      \"country\": \"USA\",\n      \"timezone\": \"America/Los_Angeles\"\n    },\n    \"preferences\": {\n      \"communication_style\": [\n        \"concise\"\n      ],\n      \"tools\": [\n        \"excel\",\n        \"google_sheets\"\n      ],\n      \"notes\": \"Prefers tables for numbers.\"\n    }\n  },\n  \"history\": [\n    {\n      \"field\": \"timezone\",\n      \"old_value\": \"America/Chicago\",\n      \"new_value\": \"America/Los_Angeles\"\n    }\n  ],\n  \"last_updated\": \"2026-02-04\"\n}"}
{"sample_id": "umm-006", "input": "Prior user_model.json:\n{\n  \"user_id\": \"u_006\",\n  \"name\": \"Zoe Lin\",\n  \"current\": {\n    \"employer\": \"Riverstone Media\",\n    \"role\": \"Content Strategist\",\n    \"location\": {\n      \"city\": \"Vancouver\",\n      \"country\": \"Canada\",\n      \"timezone\": \"America/Vancouver\"\n    },\n    \"preferences\": {\n      \"communication_style\": [\n        \"bullets\"\n      ],\n      \"tools\": [\n        \"google_docs\"\n      ],\n      \"notes\": \"Avoid jargon.\"\n    }\n  },\n  \"history\": [],\n  \"last_updated\": \"2026-01-02\"\n}\n\nRecent conversation excerpt:\nUser: Before we dive in - quick thing. I noticed my name shows up as \"Zoe\" in your system but it's actually \"Zoey\" with a y. Could you fix that going forward?\n\nAssistant: Of course, noted - Zoey Lin. What can I help with today?\n\nUser: I'm working on a brand voice guide for Riverstone Media. We're trying to shift the company's content from this very corporate, fragmented style to something more narrative-driven. My colleague Marcus - he's the Creative Director - has some strong opinions about incorporating more visual storytelling, but that's more his domain.\n\nUser: Actually, that reminds me. Can you change how you write responses to me too? I've been getting bullet points from you and honestly I'd much prefer flowing narrative paragraphs. More storytelling, less listicle, if you know what I mean. Prose style.\n\nAssistant: Absolutely, I'll switch to a narrative prose style. Makes sense given the work you're doing!\n\nUser: Yeah exactly - kind of need to eat my own cooking here. Also, I got promoted to Senior Content Strategist last month, so this brand voice project is actually my first big initiative in the new role. Marcus and I have been going back and forth on the tone spectrum - he wants something warmer, I'm pushing for authoritative but accessible. No jargon either way though, that's non-negotiable.\n\nUser: So for the guide itself, I'm thinking we structure it around three core principles. Can you help me flesh those out?\n\nRequired JSON keys:\n- user_id, name, current, history, last_updated\ncurrent.employer, current.role, current.location {city,country,timezone}, current.preferences {communication_style[], tools[], notes}\nhistory entries only for employer/role/location/timezone changes.\nOutput a single JSON object only (no code fences).", "ground_truth": "{\n  \"user_id\": \"u_006\",\n  \"name\": \"Zoey Lin\",\n  \"current\": {\n    \"employer\": \"Riverstone Media\",\n    \"role\": \"Senior Content Strategist\",\n    \"location\": {\n      \"city\": \"Vancouver\",\n      \"country\": \"Canada\",\n      \"timezone\": \"America/Vancouver\"\n    },\n    \"preferences\": {\n      \"communication_style\": [\n        \"narrative\",\n        \"prose\"\n      ],\n      \"tools\": [\n        \"google_docs\"\n      ],\n      \"notes\": \"Avoid jargon.\"\n    }\n  },\n  \"history\": [\n    {\n      \"field\": \"role\",\n      \"old_value\": \"Content Strategist\",\n      \"new_value\": \"Senior Content Strategist\"\n    }\n  ],\n  \"last_updated\": \"2026-02-04\"\n}"}
